academic_avocado_namer/__init__.py
academic_avocado_namer/__main__.py
academic_avocado_namer/__meta__.py
academic_avocado_namer/word_lists.py
academic_avocado_namer-1.0.3.dist-info/LICENSE
academic_avocado_namer-1.0.3.dist-info/METADATA
academic_avocado_namer-1.0.3.dist-info/WHEEL
academic_avocado_namer-1.0.3.dist-info/top_level.txt
academic_avocado_namer-1.0.3.dist-info/RECORD
