Metadata-Version: 2.1
Name: academic-avocado-namer
Version: 1.0.3
Summary: Generate names for things with phonetic alliteration - use with GUIDs for easy identification.
Home-page: https://github.com/darenr/academic-avocado-namer
Author: Daren Race
Author-email: daren.race@gmail.com
License: Apache License, Version 2.0, January 2004
Keywords: random name generator
Classifier: Development Status :: 5 - Production/Stable
Classifier: Topic :: Software Development :: Libraries :: Application Frameworks
Classifier: License :: OSI Approved :: Apache Software License
Classifier: Programming Language :: Python :: 3.7
Classifier: Programming Language :: Python :: 3.8
Classifier: Programming Language :: Python :: 3.9
License-File: LICENSE
